neuromorpho_api/__init__.py
neuromorpho_api/_requests.py
neuromorpho_api/tests/test_requestor.py
neuromorpho_api-0.2.dist-info/LICENSE
neuromorpho_api-0.2.dist-info/METADATA
neuromorpho_api-0.2.dist-info/WHEEL
neuromorpho_api-0.2.dist-info/top_level.txt
neuromorpho_api-0.2.dist-info/RECORD
