Metadata-Version: 2.1
Name: neuromorpho_api
Version: 0.2
Summary: Querying neuromorpho.org database with Python requests
Author-email: Ross Barnowski <rossbar@caltech.edu>
Project-URL: Source Code, https://github.com/rossbar/neuromorpho-api
Project-URL: Documentation, https://neuromorpho-api.readthedocs.io/en/latest/
Project-URL: Issue Tracker, https://github.com/rossbar/neuromorpho-api/issues
Keywords: neuromorpho.org,neuromorpho API,neuron
Classifier: Programming Language :: Python :: 3
Classifier: License :: OSI Approved :: BSD License
Classifier: Operating System :: OS Independent
Requires-Python: >=3.8
License-File: LICENSE
Requires-Dist: urllib3
Requires-Dist: requests
